[
  {
    "greek_words": [
      { "greek": "Καὶ", "latvian": ["Un"] },
      { "greek": "πάλιν", "latvian": ["atkal"] },
      { "greek": "ἤρξατο", "latvian": ["sāka"] },
      { "greek": "διδάσκειν", "latvian": ["mācīt"] },
      { "greek": "παρὰ", "latvian": ["pie"] },
      { "greek": "τὴν", "latvian": [] },
      { "greek": "θάλασσαν", "latvian": ["jūras"] },
      { "greek": "καὶ", "latvian": ["Un"] },
      { "greek": "συνάγεται", "latvian": ["sapulcējās"] },
      { "greek": "πρὸς", "latvian": ["pie"] },
      { "greek": "αὐτὸν", "latvian": ["Viņa"] },
      { "greek": "ὄχλος", "latvian": ["ļaužu"] },
      { "greek": "πλεῖστος", "latvian": ["daudz"] },
      { "greek": "ὥστε", "latvian": ["tā", "ka"] },
      { "greek": "αὐτὸν", "latvian": ["Viņš"] },
      { "greek": "εἰς", "latvian": [] },
      { "greek": "πλοῖον", "latvian": ["laivā"] },
      { "greek": "ἐμβάντα", "latvian": ["iekāpa"] },
      { "greek": "καθῆσθαι", "latvian": ["apsēdās"] },
      { "greek": "ἐν", "latvian": ["uz"] },
      { "greek": "τῇ", "latvian": [] },
      { "greek": "θαλάσσῃ", "latvian": ["jūras"] },
      { "greek": "καὶ", "latvian": ["un"] },
      { "greek": "πᾶς", "latvian": ["visi"] },
      { "greek": "ὁ", "latvian": [] },
      { "greek": "ὄχλος", "latvian": ["ļaudis"] },
      { "greek": "πρὸς", "latvian": [] },
      { "greek": "τὴν", "latvian": [] },
      { "greek": "θάλασσαν", "latvian": ["jūras"] },
      { "greek": "ἐπὶ", "latvian": [] },
      { "greek": "τῆς", "latvian": [] },
      { "greek": "γῆς", "latvian": ["malā"] },
      { "greek": "ἦσαν", "latvian": ["stāvēja"] }
    ],
    "leftover_latvian": ["Viņš", "Viņš", "bija", "Un"]
  },
  {
    "greek_words": [
      { "greek": "Καὶ", "latvian": ["Un"] },
      { "greek": "ἐδίδασκεν", "latvian": ["mācīja"] },
      { "greek": "αὐτοὺς", "latvian": ["tiem"] },
      { "greek": "ἐν", "latvian": [] },
      { "greek": "παραβολαῖς", "latvian": ["līdzībās"] },
      { "greek": "πολλά", "latvian": ["daudz"] },
      { "greek": "καὶ", "latvian": ["un"] },
      { "greek": "ἔλεγεν", "latvian": ["sacīja"] },
      { "greek": "αὐτοῖς", "latvian": ["tiem"] },
      { "greek": "ἐν", "latvian": [] },
      { "greek": "τῇ", "latvian": [] },
      { "greek": "διδαχῇ", "latvian": ["mācībā"] },
      { "greek": "αὐτοῦ", "latvian": ["Savā"] }
    ],
    "leftover_latvian": ["Viņš", "uz"]
  },
  {
    "greek_words": [
      { "greek": "Ἀκούετε", "latvian": ["Klausaities"] },
      { "greek": "ἰδοὺ", "latvian": ["raugi"] },
      { "greek": "ἐξῆλθεν", "latvian": ["izgāja"] },
      { "greek": "ὁ", "latvian": [] },
      { "greek": "σπείρων", "latvian": ["sējējs"] },
      { "greek": "σπεῖραι", "latvian": ["sēt"] }
    ],
    "leftover_latvian": []
  },
  {
    "greek_words": [
      { "greek": "καὶ", "latvian": ["Un"] },
      { "greek": "ἐγένετο", "latvian": ["notika"] },
      { "greek": "ἐν", "latvian": [] },
      { "greek": "τῷ", "latvian": [] },
      { "greek": "σπείρειν", "latvian": ["sējot"] },
      { "greek": "ὃ", "latvian": ["cita"] },
      { "greek": "μὲν", "latvian": [] },
      { "greek": "ἔπεσεν", "latvian": ["krita"] },
      { "greek": "παρὰ", "latvian": ["ceļmalā"] },
      { "greek": "τὴν", "latvian": [] },
      { "greek": "ὁδόν", "latvian": [] },
      { "greek": "καὶ", "latvian": ["un"] },
      { "greek": "ἦλθεν", "latvian": ["nāca"] },
      { "greek": "τὰ", "latvian": [] },
      { "greek": "πετεινὰ", "latvian": ["putni"] },
      { "greek": "καὶ", "latvian": ["un"] },
      { "greek": "κατέφαγεν", "latvian": ["apēda"] },
      { "greek": "αὐτό", "latvian": ["to"] }
    ],
    "leftover_latvian": ["sēkla"]
  },
  {
    "greek_words": [
      { "greek": "Καὶ", "latvian": ["Un"] },
      { "greek": "ἄλλο", "latvian": ["cita"] },
      { "greek": "ἔπεσεν", "latvian": ["krita"] },
      { "greek": "ἐπὶ", "latvian": ["uz"] },
      { "greek": "τὸ", "latvian": [] },
      { "greek": "πετρῶδες", "latvian": ["akmenāju"] },
      { "greek": "καὶ", "latvian": ["un"] },
      { "greek": "ὅπου", "latvian": ["kur"] },
      { "greek": "οὐκ", "latvian": ["nebija"] },
      { "greek": "εἶχεν", "latvian": ["nebija"] },
      { "greek": "γῆν", "latvian": ["zemes"] },
      { "greek": "πολλήν", "latvian": ["daudz"] },
      { "greek": "καὶ", "latvian": [] },
      { "greek": "εὐθὺς", "latvian": ["tūdaļ"] },
      { "greek": "ἐξανέτειλεν", "latvian": ["uzdīga"] },
      { "greek": "διὰ", "latvian": ["tāpēc"] },
      { "greek": "τὸ", "latvian": [] },
      { "greek": "μὴ", "latvian": [] },
      { "greek": "ἔχειν", "latvian": [] },
      { "greek": "βάθος", "latvian": ["dziļas"] },
      { "greek": "γῆς", "latvian": ["zemes"] }
    ],
    "leftover_latvian": ["tai", "tā", "ka", "tai"]
  },
  {
    "greek_words": [
      { "greek": "καὶ", "latvian": ["un"] },
      { "greek": "ὅτε", "latvian": ["kad"] },
      { "greek": "ἀνέτειλεν", "latvian": ["uzlēkusi"] },
      { "greek": "ὁ", "latvian": [] },
      { "greek": "ἥλιος", "latvian": ["saule"] },
      { "greek": "ἐκαυματίσθη", "latvian": ["nokalta"] },
      { "greek": "καὶ", "latvian": [] },
      { "greek": "διὰ", "latvian": ["tāpēc"] },
      { "greek": "τὸ", "latvian": [] },
      { "greek": "μὴ", "latvian": [] },
      { "greek": "ἔχειν", "latvian": ["bija"] },
      { "greek": "ῥίζαν", "latvian": ["saknes"] },
      { "greek": "ἐξηράνθη", "latvian": [] }
    ],
    "leftover_latvian": ["Bet", "tad", "tā", "savīta", "ka", "tai", "nebija"]
  },
  {
    "greek_words": [
      { "greek": "Καὶ", "latvian": ["Un"] },
      { "greek": "ἄλλο", "latvian": ["cita"] },
      { "greek": "ἔπεσεν", "latvian": ["krita"] },
      { "greek": "εἰς", "latvian": ["starp"] },
      { "greek": "τὰς", "latvian": [] },
      { "greek": "ἀκάνθας", "latvian": ["ērkšķiem"] },
      { "greek": "καὶ", "latvian": ["un"] },
      { "greek": "ἀνέβησαν", "latvian": ["uzauga"] },
      { "greek": "αἱ", "latvian": [] },
      { "greek": "ἄκανθαι", "latvian": ["ērkšķi"] },
      { "greek": "καὶ", "latvian": ["un"] },
      { "greek": "συνέπνιξαν", "latvian": ["nomāca"] },
      { "greek": "αὐτό", "latvian": ["to"] },
      { "greek": "καὶ", "latvian": ["un"] },
      { "greek": "καρπὸν", "latvian": ["augļus"] },
      { "greek": "οὐκ", "latvian": ["nenesa"] },
      { "greek": "ἔδωκεν", "latvian": [] }
    ],
    "leftover_latvian": ["tā"]
  },
  {
    "greek_words": [
      { "greek": "Καὶ", "latvian": ["Un"] },
      { "greek": "ἄλλα", "latvian": ["cita"] },
      { "greek": "ἔπεσεν", "latvian": ["krita"] },
      { "greek": "εἰς", "latvian": [] },
      { "greek": "τὴν", "latvian": [] },
      { "greek": "γῆν", "latvian": ["zemē"] },
      { "greek": "τὴν", "latvian": [] },
      { "greek": "καλήν", "latvian": ["labā"] },
      { "greek": "καὶ", "latvian": ["un"] },
      { "greek": "ἐδίδου", "latvian": ["nesa"] },
      { "greek": "καρπὸν", "latvian": ["augļus"] },
      { "greek": "ἀναβαίνοντα", "latvian": ["uzdīga"] },
      { "greek": "καὶ", "latvian": ["un"] },
      { "greek": "αὐξανόμενα", "latvian": ["augtin", "auga"] },
      { "greek": "καὶ", "latvian": ["un"] },
      { "greek": "ἔφερεν", "latvian": ["nesa"] },
      { "greek": "ἓν", "latvian": [] },
      { "greek": "τριάκοντα", "latvian": ["trīsdesmitkārtīgi"] },
      { "greek": "καὶ", "latvian": ["un"] },
      { "greek": "ἓν", "latvian": [] },
      { "greek": "ἑξήκοντα", "latvian": ["sešdesmitkārtīgi"] },
      { "greek": "καὶ", "latvian": [] },
      { "greek": "ἓν", "latvian": [] },
      { "greek": "ἑκατόν", "latvian": ["simtkārtīgi"] }
    ],
    "leftover_latvian": ["kas", "cita", "cita", "cita"]
  },
  {
    "greek_words": [
      { "greek": "Καὶ", "latvian": ["Un"] },
      { "greek": "ἔλεγεν", "latvian": ["sacīja"] },
      { "greek": "Ὃς", "latvian": ["Kam"] },
      { "greek": "ἔχει", "latvian": [] },
      { "greek": "ὦτα", "latvian": ["ausis"] },
      { "greek": "ἀκούειν", "latvian": ["dzirdēt"] },
      { "greek": "ἀκουέτω", "latvian": ["lai", "dzird"] }
    ],
    "leftover_latvian": ["Viņš", "tas"]
  },
  {
    "greek_words": [
      { "greek": "Καὶ", "latvian": ["Un"] },
      { "greek": "ὅτε", "latvian": ["kad"] },
      { "greek": "ἐγένετο", "latvian": ["bija"] },
      { "greek": "κατὰ", "latvian": [] },
      { "greek": "μόνας", "latvian": ["pats"] },
      { "greek": "ἠρώτων", "latvian": ["vaicāja"] },
      { "greek": "αὐτὸν", "latvian": ["Viņam"] },
      { "greek": "οἱ", "latvian": ["tie"] },
      { "greek": "περὶ", "latvian": ["pie"] },
      { "greek": "αὐτὸν", "latvian": ["Viņa"] },
      { "greek": "σὺν", "latvian": ["līdz", "ar"] },
      { "greek": "τοῖς", "latvian": ["tiem"] },
      { "greek": "δώδεκα", "latvian": ["divpadsmit"] },
      { "greek": "τὰς", "latvian": ["par"] },
      { "greek": "παραβολάς", "latvian": ["līdzībām"] }
    ],
    "leftover_latvian": ["Viņš", "viens", "tad", "kas", "bija"]
  },
  {
    "greek_words": [
      { "greek": "Καὶ", "latvian": ["Un"] },
      { "greek": "ἔλεγεν", "latvian": ["sacīja"] },
      { "greek": "αὐτοῖς", "latvian": ["tiem"] },
      { "greek": "Ὑμῖν", "latvian": ["Jums"] },
      { "greek": "τὸ", "latvian": [] },
      { "greek": "μυστήριον", "latvian": ["noslēpums;"] },
      { "greek": "δέδοται", "latvian": ["dots"] },
      { "greek": "τῆς", "latvian": [] },
      { "greek": "βασιλείας", "latvian": ["valstības"] },
      { "greek": "τοῦ", "latvian": [] },
      { "greek": "Θεοῦ", "latvian": ["Dieva"] },
      { "greek": "ἐκείνοις", "latvian": ["tiem"] },
      { "greek": "δὲ", "latvian": ["bet"] },
      { "greek": "τοῖς", "latvian": [] },
      { "greek": "ἔξω", "latvian": ["ārā"] },
      { "greek": "ἐν", "latvian": [] },
      { "greek": "παραβολαῖς", "latvian": ["līdzībās"] },
      { "greek": "τὰ", "latvian": [] },
      { "greek": "πάντα", "latvian": ["viss"] },
      { "greek": "γίνεται", "latvian": ["notiek"] }
    ],
    "leftover_latvian": ["Viņš", "uz", "ir", "kas", "tas"]
  },
  {
    "greek_words": [
      { "greek": "ἵνα", "latvian": ["ka"] },
      { "greek": "Βλέποντες", "latvian": ["tie", "redzēdami"] },
      { "greek": "βλέπωσιν", "latvian": ["redz"] },
      { "greek": "καὶ", "latvian": ["un"] },
      { "greek": "μὴ", "latvian": ["ne-"] },
      { "greek": "ἴδωσιν", "latvian": ["- nomana"] },
      { "greek": "Καὶ", "latvian": ["un"] },
      { "greek": "ἀκούοντες", "latvian": ["dzirdēdami"] },
      { "greek": "ἀκούωσιν", "latvian": ["dzird"] },
      { "greek": "καὶ", "latvian": ["un"] },
      { "greek": "μὴ", "latvian": [] },
      { "greek": "συνιῶσιν", "latvian": ["saprot"] },
      { "greek": "Μή", "latvian": [] },
      { "greek": "ποτε", "latvian": ["ka", "tie"] },
      { "greek": "ἐπιστρέψωσιν", "latvian": ["- atgriežas"] },
      { "greek": "Καὶ", "latvian": ["un"] },
      { "greek": "ἀφεθῇ", "latvian": ["- iegūst", "piedošanu"] },
      { "greek": "αὐτοῖς", "latvian": [] }
    ],
    "leftover_latvian": []
  },
  {
    "greek_words": [
      { "greek": "Καὶ", "latvian": ["Un"] },
      { "greek": "λέγει", "latvian": ["Viņš", "saka"] },
      { "greek": "αὐτοῖς", "latvian": ["uz", "tiem"] },
      { "greek": "Οὐκ", "latvian": ["ne-"] },
      { "greek": "οἴδατε", "latvian": ["- saprotat", "Jūs"] },
      { "greek": "τὴν", "latvian": [] },
      { "greek": "παραβολὴν", "latvian": ["līdzību"] },
      { "greek": "ταύτην", "latvian": ["šo"] },
      { "greek": "καὶ", "latvian": [] },
      { "greek": "πῶς", "latvian": ["kā", "tad"] },
      { "greek": "πάσας", "latvian": ["visas", "citas"] },
      { "greek": "τὰς", "latvian": [] },
      { "greek": "παραβολὰς", "latvian": ["līdzības"] },
      { "greek": "γνώσεσθε", "latvian": ["jūs", "sapratīsit"] }
    ],
    "leftover_latvian": []
  },
  {
    "greek_words": [
      { "greek": "Ὁ", "latvian": [] },
      { "greek": "σπείρων", "latvian": ["sējējs"] },
      { "greek": "τὸν", "latvian": [] },
      { "greek": "λόγον", "latvian": ["vārdu"] },
      { "greek": "σπείρει", "latvian": ["sēj"] }
    ],
    "leftover_latvian": []
  },
  {
    "greek_words": [
      { "greek": "οὗτοι", "latvian": ["šie"] },
      { "greek": "δέ", "latvian": ["Bet"] },
      { "greek": "εἰσιν", "latvian": ["ir"] },
      { "greek": "οἱ", "latvian": ["tie"] },
      { "greek": "παρὰ", "latvian": [] },
      { "greek": "τὴν", "latvian": [] },
      { "greek": "ὁδὸν", "latvian": ["ceļmalā"] },
      { "greek": "ὅπου", "latvian": ["kur"] },
      { "greek": "σπείρεται", "latvian": ["top", "sēts"] },
      { "greek": "ὁ", "latvian": [] },
      { "greek": "λόγος", "latvian": ["vārds"] },
      { "greek": "καὶ", "latvian": ["un"] },
      { "greek": "ὅταν", "latvian": ["kad"] },
      { "greek": "ἀκούσωσιν", "latvian": ["dzirdējuši"] },
      { "greek": "εὐθὺς", "latvian": ["tūdaļ"] },
      { "greek": "ἔρχεται", "latvian": ["nāk"] },
      { "greek": "ὁ", "latvian": [] },
      { "greek": "Σατανᾶς", "latvian": ["sātans"] },
      { "greek": "καὶ", "latvian": [] },
      { "greek": "αἴρει", "latvian": ["noņem"] },
      { "greek": "τὸν", "latvian": [] },
      { "greek": "λόγον", "latvian": ["vārdu"] },
      { "greek": "τὸν", "latvian": [] },
      { "greek": "ἐσπαρμένον", "latvian": ["sēto"] },
      { "greek": "εἰς", "latvian": ["sirdīs"] },
      { "greek": "αὐτούς", "latvian": ["viņu"] }
    ],
    "leftover_latvian": ["kas", "pie", "kuriem", "tie", "to", "ir"]
  },
  {
    "greek_words": [
      { "greek": "Καὶ", "latvian": ["Un"] },
      { "greek": "οὗτοί", "latvian": ["tie"] },
      { "greek": "εἰσιν", "latvian": ["ir"] },
      { "greek": "ὁμοίως", "latvian": ["tāpat"] },
      { "greek": "οἱ", "latvian": ["tie"] },
      { "greek": "ἐπὶ", "latvian": ["uz"] },
      { "greek": "τὰ", "latvian": [] },
      { "greek": "πετρώδη", "latvian": ["akmenāju"] },
      { "greek": "σπειρόμενοι", "latvian": ["sēti"] },
      { "greek": "οἳ", "latvian": ["kas"] },
      { "greek": "ὅταν", "latvian": [] },
      { "greek": "ἀκούσωσιν", "latvian": ["dzirdējuši"] },
      { "greek": "τὸν", "latvian": [] },
      { "greek": "λόγον", "latvian": ["vārdu"] },
      { "greek": "εὐθὺς", "latvian": ["tūdaļ"] },
      { "greek": "μετὰ", "latvian": ["ar"] },
      { "greek": "χαρᾶς", "latvian": ["prieku"] },
      { "greek": "λαμβάνουσιν", "latvian": ["uzņem"] },
      { "greek": "αὐτόν", "latvian": ["to"] }
    ],
    "leftover_latvian": ["kas"]
  },
  {
    "greek_words": [
      { "greek": "καὶ", "latvian": ["Bet"] },
      { "greek": "οὐκ", "latvian": ["nav"] },
      { "greek": "ἔχουσιν", "latvian": ["tiem"] },
      { "greek": "ῥίζαν", "latvian": ["saknes"] },
      { "greek": "ἐν", "latvian": ["sevī"] },
      { "greek": "ἑαυτοῖς", "latvian": [] },
      { "greek": "ἀλλὰ", "latvian": ["un"] },
      { "greek": "πρόσκαιροί", "latvian": ["tikai"] },
      { "greek": "εἰσιν", "latvian": ["laiku"] },
      { "greek": "εἶτα", "latvian": ["Kad"] },
      { "greek": "γενομένης", "latvian": ["bēdas"] },
      { "greek": "θλίψεως", "latvian": [] },
      { "greek": "ἢ", "latvian": ["un"] },
      { "greek": "διωγμοῦ", "latvian": ["vajāšanas"] },
      { "greek": "διὰ", "latvian": ["uziet"] },
      { "greek": "τὸν", "latvian": ["vārda"] },
      { "greek": "λόγον", "latvian": ["dēļ"] },
      { "greek": "εὐθὺς", "latvian": ["tūdaļ"] },
      { "greek": "σκανδαλίζονται", "latvian": ["apgrēkojas"] }
    ],
    "leftover_latvian": ["kādu", "tie", "ir", "ticīgi", "tad", "viņi"]
  },
  {
    "greek_words": [
      { "greek": "Καὶ", "latvian": ["Un"] },
      { "greek": "ἄλλοι", "latvian": ["kas"] },
      { "greek": "εἰσὶν", "latvian": ["starp"] },
      { "greek": "οἱ", "latvian": ["ērkšķiem"] },
      { "greek": "εἰς", "latvian": ["sēti"] },
      { "greek": "τὰς", "latvian": ["ir"] },
      { "greek": "ἀκάνθας", "latvian": ["tie"] },
      { "greek": "σπειρόμενοι", "latvian": ["kas"] },
      { "greek": "οὗτοί", "latvian": ["vārdu"] },
      { "greek": "εἰσιν", "latvian": ["dzird"] },
      { "greek": "οἱ", "latvian": [] },
      { "greek": "τὸν", "latvian": [] },
      { "greek": "λόγον", "latvian": [] },
      { "greek": "ἀκούσαντες", "latvian": [] }
    ],
    "leftover_latvian": []
  },
  {
    "greek_words": [
      { "greek": "καὶ", "latvian": ["un"] },
      { "greek": "αἱ", "latvian": ["šīs"] },
      { "greek": "μέριμναι", "latvian": ["rūpes"] },
      { "greek": "τοῦ", "latvian": [] },
      { "greek": "αἰῶνος", "latvian": ["pasaules"] },
      { "greek": "καὶ", "latvian": ["un"] },
      { "greek": "ἡ", "latvian": [] },
      { "greek": "ἀπάτη", "latvian": ["viltība"] },
      { "greek": "τοῦ", "latvian": [] },
      { "greek": "πλούτου", "latvian": ["bagātības"] },
      { "greek": "καὶ", "latvian": ["un"] },
      { "greek": "αἱ", "latvian": ["citas"] },
      { "greek": "περὶ", "latvian": [] },
      { "greek": "τὰ", "latvian": [] },
      { "greek": "λοιπὰ", "latvian": [] },
      { "greek": "ἐπιθυμίαι", "latvian": ["kārības"] },
      { "greek": "εἰσπορευόμεναι", "latvian": ["iemetas"] },
      { "greek": "συμπνίγουσιν", "latvian": ["noslāpē"] },
      { "greek": "τὸν", "latvian": [] },
      { "greek": "λόγον", "latvian": ["vārdu"] },
      { "greek": "καὶ", "latvian": ["un"] },
      { "greek": "ἄκαρπος", "latvian": ["neauglīgs"] },
      { "greek": "γίνεται", "latvian": ["kļūst"] }
    ],
    "leftover_latvian": ["tas", "un"]
  },
  {
    "greek_words": [
      { "greek": "Καὶ", "latvian": ["Un"] },
      { "greek": "ἐκεῖνοί", "latvian": ["tie"] },
      { "greek": "εἰσιν", "latvian": ["ir"] },
      { "greek": "οἱ", "latvian": [] },
      { "greek": "ἐπὶ", "latvian": [] },
      { "greek": "τὴν", "latvian": [] },
      { "greek": "γῆν", "latvian": ["zemē"] },
      { "greek": "τὴν", "latvian": [] },
      { "greek": "καλὴν", "latvian": ["labā"] },
      { "greek": "σπαρέντες", "latvian": ["sētie"] },
      { "greek": "οἵτινες", "latvian": ["kas"] },
      { "greek": "ἀκούουσιν", "latvian": ["dzird"] },
      { "greek": "τὸν", "latvian": [] },
      { "greek": "λόγον", "latvian": ["vārdu"] },
      { "greek": "καὶ", "latvian": ["un"] },
      { "greek": "παραδέχονται", "latvian": ["pieņem"] },
      { "greek": "καὶ", "latvian": ["un"] },
      { "greek": "καρποφοροῦσιν", "latvian": ["augļus", "nes"] },
      { "greek": "ἓν", "latvian": [] },
      { "greek": "τριάκοντα", "latvian": ["trīsdesmitkārtīgus"] },
      { "greek": "καὶ", "latvian": [] },
      { "greek": "ἓν", "latvian": [] },
      { "greek": "ἑξήκοντα", "latvian": ["sešdesmitkārtīgus"] },
      { "greek": "καὶ", "latvian": [] },
      { "greek": "ἓν", "latvian": [] },
      { "greek": "ἑκατόν", "latvian": ["simtkārtīgus"] }
    ],
    "leftover_latvian": []
  },
  {
    "greek_words": [
      { "greek": "Καὶ", "latvian": ["Un"] },
      { "greek": "ἔλεγεν", "latvian": ["sacīja"] },
      { "greek": "αὐτοῖς", "latvian": ["tiem"] },
      { "greek": "ὅτι", "latvian": ["Vai"] },
      { "greek": "Μήτι", "latvian": ["Vai"] },
      { "greek": "ἔρχεται", "latvian": ["iededzina"] },
      { "greek": "ὁ", "latvian": [] },
      { "greek": "λύχνος", "latvian": ["sveci"] },
      { "greek": "ἵνα", "latvian": ["lai"] },
      { "greek": "ὑπὸ", "latvian": ["apakš"] },
      { "greek": "τὸν", "latvian": ["pūra"] },
      { "greek": "μόδιον", "latvian": [] },
      { "greek": "τεθῇ", "latvian": ["liktu"] },
      { "greek": "ἢ", "latvian": ["vai"] },
      { "greek": "ὑπὸ", "latvian": ["zem"] },
      { "greek": "τὴν", "latvian": ["gultas"] },
      { "greek": "κλίνην", "latvian": [] },
      { "greek": "οὐχ", "latvian": ["ne"] },
      { "greek": "ἵνα", "latvian": ["lai"] },
      { "greek": "ἐπὶ", "latvian": [] },
      { "greek": "τὴν", "latvian": [] },
      { "greek": "λυχνίαν", "latvian": ["lukturī"] },
      { "greek": "τεθῇ", "latvian": ["liek"] }
    ],
    "leftover_latvian": ["Viņš", "uz", "to", "tāpēc", "to"]
  },
  {
    "greek_words": [
      { "greek": "οὐ", "latvian": ["nav"] },
      { "greek": "γάρ", "latvian": ["Jo"] },
      { "greek": "ἐστιν", "latvian": [] },
      { "greek": "τι", "latvian": ["nekas"] },
      { "greek": "κρυπτὸν", "latvian": ["apslēpts"] },
      { "greek": "ἐὰν", "latvian": ["kas"] },
      { "greek": "μὴ", "latvian": ["nenāktu"] },
      { "greek": "ἵνα", "latvian": [] },
      { "greek": "φανερωθῇ", "latvian": ["gaismā;"] },
      { "greek": "οὐδὲ", "latvian": ["un"] },
      { "greek": "ἐγένετο", "latvian": ["nenotiek"] },
      { "greek": "ἀπόκρυφον", "latvian": ["slepeni"] },
      { "greek": "ἀλλ", "latvian": ["kas"] },
      { "greek": "ἵνα", "latvian": ["netaptu"] },
      { "greek": "ἔλθῃ", "latvian": [] },
      { "greek": "εἰς", "latvian": ["zināms"] },
      { "greek": "φανερόν", "latvian": [] }
    ],
    "leftover_latvian": ["nekas"]
  },
  {
    "greek_words": [
      { "greek": "Εἴ", "latvian": ["Ja"] },
      { "greek": "τις", "latvian": ["kam"] },
      { "greek": "ἔχει", "latvian": ["ir"] },
      { "greek": "ὦτα", "latvian": ["ausis"] },
      { "greek": "ἀκούειν", "latvian": ["dzirdēt"] },
      { "greek": "ἀκουέτω", "latvian": ["lai", "dzird"] }
    ],
    "leftover_latvian": ["tas"]
  },
  {
    "greek_words": [
      { "greek": "Καὶ", "latvian": ["Un"] },
      { "greek": "ἔλεγεν", "latvian": ["sacīja"] },
      { "greek": "αὐτοῖς", "latvian": ["tiem"] },
      { "greek": "Βλέπετε", "latvian": ["Ievērojiet"] },
      { "greek": "τί", "latvian": ["ko"] },
      { "greek": "ἀκούετε", "latvian": ["dzirdat"] },
      { "greek": "ἐν", "latvian": ["Ar"] },
      { "greek": "ᾧ", "latvian": ["kādu"] },
      { "greek": "μέτρῳ", "latvian": ["mēru"] },
      { "greek": "μετρεῖτε", "latvian": ["mērojat"] },
      { "greek": "μετρηθήσεται", "latvian": ["mēros"] },
      { "greek": "ὑμῖν", "latvian": ["jums"] },
      { "greek": "καὶ", "latvian": ["un"] },
      { "greek": "προστεθήσεται", "latvian": ["pieliks"] },
      { "greek": "ὑμῖν", "latvian": ["jums"] }
    ],
    "leftover_latvian": ["Viņš", "jūs", "jūs", "vēl", "klāt"]
  },
  {
    "greek_words": [
      { "greek": "ὃς", "latvian": ["kas"] },
      { "greek": "γὰρ", "latvian": ["Jo"] },
      { "greek": "ἔχει", "latvian": ["ir"] },
      { "greek": "δοθήσεται", "latvian": ["dos"] },
      { "greek": "αὐτῷ", "latvian": ["tam"] },
      { "greek": "καὶ", "latvian": ["un"] },
      { "greek": "ὃς", "latvian": [] },
      { "greek": "οὐκ", "latvian": ["nav"] },
      { "greek": "ἔχει", "latvian": ["ir"] },
      { "greek": "καὶ", "latvian": [] },
      { "greek": "ὃ", "latvian": ["to"] },
      { "greek": "ἔχει", "latvian": [] },
      { "greek": "ἀρθήσεται", "latvian": ["atņems"] },
      { "greek": "ἀπ", "latvian": [] },
      { "greek": "αὐτοῦ", "latvian": [] }
    ],
    "leftover_latvian": ["kam", "kam", "arī", "tam", "tam"]
  },
  {
    "greek_words": [
      { "greek": "Καὶ", "latvian": ["Un"] },
      { "greek": "ἔλεγεν", "latvian": ["Viņš", "sacīja"] },
      { "greek": "Οὕτως", "latvian": ["Tāpat"] },
      { "greek": "ἐστὶν", "latvian": ["ir"] },
      { "greek": "ἡ", "latvian": [] },
      { "greek": "βασιλεία", "latvian": ["valstību"] },
      { "greek": "τοῦ", "latvian": [] },
      { "greek": "Θεοῦ", "latvian": ["Dieva"] },
      { "greek": "ὡς", "latvian": ["kā"] },
      { "greek": "ἄνθρωπος", "latvian": ["kāds", "cilvēks"] },
      { "greek": "βάλῃ", "latvian": ["iemet"] },
      { "greek": "τὸν", "latvian": [] },
      { "greek": "σπόρον", "latvian": ["sēklu"] },
      { "greek": "ἐπὶ", "latvian": [] },
      { "greek": "τῆς", "latvian": [] },
      { "greek": "γῆς", "latvian": ["zemē"] }
    ],
    "leftover_latvian": ["ar", "kad"]
  },
  {
    "greek_words": [
      { "greek": "καὶ", "latvian": ["un"] },
      { "greek": "καθεύδῃ", "latvian": ["guļ"] },
      { "greek": "καὶ", "latvian": ["un"] },
      { "greek": "ἐγείρηται", "latvian": ["ceļas"] },
      { "greek": "νύκτα", "latvian": ["nakti"] },
      { "greek": "καὶ", "latvian": ["un"] },
      { "greek": "ἡμέραν", "latvian": ["dienu;"] },
      { "greek": "καὶ", "latvian": ["un"] },
      { "greek": "ὁ", "latvian": [] },
      { "greek": "σπόρος", "latvian": ["sēkla"] },
      { "greek": "βλαστᾷ", "latvian": ["uzdīgst"] },
      { "greek": "καὶ", "latvian": ["un"] },
      { "greek": "μηκύνηται", "latvian": ["uzaug"] },
      { "greek": "ὡς", "latvian": ["tā"] },
      { "greek": "οὐκ", "latvian": [] },
      { "greek": "οἶδεν", "latvian": [] },
      { "greek": "αὐτός", "latvian": ["pats"] }
    ],
    "leftover_latvian": ["ka", "viņš", "to", "nenomana"]
  },
  {
    "greek_words": [
      { "greek": "αὐτομάτη", "latvian": [] },
      { "greek": "ἡ", "latvian": [] },
      { "greek": "γῆ", "latvian": ["Zeme"] },
      { "greek": "καρποφορεῖ", "latvian": ["nes"] },
      { "greek": "πρῶτον", "latvian": ["papriekš"] },
      { "greek": "χόρτον", "latvian": ["stiebru"] },
      { "greek": "εἶτα", "latvian": ["tad"] },
      { "greek": "στάχυν", "latvian": ["vārpu"] },
      { "greek": "εἶτα", "latvian": ["tad"] },
      { "greek": "πλήρης", "latvian": ["briedušus"] },
      { "greek": "σῖτον", "latvian": ["graudus"] },
      { "greek": "ἐν", "latvian": [] },
      { "greek": "τῷ", "latvian": [] },
      { "greek": "στάχυϊ", "latvian": ["vārpā"] }
    ],
    "leftover_latvian": ["no", "sevis", "augļus", "pati"]
  },
  {
    "greek_words": [
      { "greek": "ὅταν", "latvian": ["kad"] },
      { "greek": "δὲ", "latvian": ["tad"] },
      { "greek": "παραδοῖ", "latvian": ["ienākušies"] },
      { "greek": "ὁ", "latvian": [] },
      { "greek": "καρπός", "latvian": ["augļi"] },
      { "greek": "εὐθὺς", "latvian": ["tūdaļ"] },
      { "greek": "ἀποστέλλει", "latvian": ["sūta"] },
      { "greek": "τὸ", "latvian": [] },
      { "greek": "δρέπανον", "latvian": ["sirpi"] },
      { "greek": "ὅτι", "latvian": ["jo"] },
      { "greek": "παρέστηκεν", "latvian": ["ir"] },
      { "greek": "ὁ", "latvian": ["pļaujamais"] },
      { "greek": "θερισμός", "latvian": ["laiks"] }
    ],
    "leftover_latvian": ["Un", "viņš", "klāt"]
  },
  {
    "greek_words": [
      { "greek": "Καὶ", "latvian": ["Un"] },
      { "greek": "ἔλεγεν", "latvian": ["sacīja"] },
      { "greek": "Πῶς", "latvian": ["Kam"] },
      { "greek": "ὁμοιώσωμεν", "latvian": ["pielīdzināsim"] },
      { "greek": "τὴν", "latvian": [] },
      { "greek": "βασιλείαν", "latvian": ["valstību"] },
      { "greek": "τοῦ", "latvian": [] },
      { "greek": "Θεοῦ", "latvian": ["Dieva"] },
      { "greek": "ἢ", "latvian": ["Jeb"] },
      { "greek": "ἐν", "latvian": [] },
      { "greek": "τίνι", "latvian": ["kādā"] },
      { "greek": "αὐτὴν", "latvian": ["to"] },
      { "greek": "παραβολῇ", "latvian": ["līdzībā"] },
      { "greek": "θῶμεν", "latvian": ["tēlosim"] }
    ],
    "leftover_latvian": ["Viņš", "mēs", "mēs"]
  },
  {
    "greek_words": [
      { "greek": "ὡς", "latvian": ["Kā"] },
      { "greek": "κόκκῳ", "latvian": ["graudiņš"] },
      { "greek": "σινάπεως", "latvian": ["sinepju"] },
      { "greek": "ὃς", "latvian": ["kas"] },
      { "greek": "ὅταν", "latvian": [] },
      { "greek": "σπαρῇ", "latvian": ["sēts"] },
      { "greek": "ἐπὶ", "latvian": [] },
      { "greek": "τῆς", "latvian": [] },
      { "greek": "γῆς", "latvian": ["zemē"] },
      { "greek": "μικρότερον", "latvian": ["mazākais"] },
      { "greek": "ὂν", "latvian": ["ir"] },
      { "greek": "πάντων", "latvian": ["visām"] },
      { "greek": "τῶν", "latvian": [] },
      { "greek": "σπερμάτων", "latvian": ["sēklām"] },
      { "greek": "τῶν", "latvian": ["no"] },
      { "greek": "ἐπὶ", "latvian": ["virs"] },
      { "greek": "τῆς", "latvian": [] },
      { "greek": "γῆς", "latvian": ["zemes"] }
    ],
    "leftover_latvian": []
  },
  {
    "greek_words": [
      { "greek": "καὶ", "latvian": ["un"] },
      { "greek": "ὅταν", "latvian": ["kad"] },
      { "greek": "σπαρῇ", "latvian": ["sēts"] },
      { "greek": "ἀναβαίνει", "latvian": ["augtin", "aug"] },
      { "greek": "καὶ", "latvian": ["un"] },
      { "greek": "γίνεται", "latvian": ["top"] },
      { "greek": "μεῖζον", "latvian": ["lielāks"] },
      { "greek": "πάντων", "latvian": ["visiem"] },
      { "greek": "τῶν", "latvian": ["dārza"] },
      { "greek": "λαχάνων", "latvian": ["augiem"] },
      { "greek": "καὶ", "latvian": ["un"] },
      { "greek": "ποιεῖ", "latvian": ["dabū"] },
      { "greek": "κλάδους", "latvian": ["zarus"] },
      { "greek": "μεγάλους", "latvian": ["lielus"] },
      { "greek": "ὥστε", "latvian": ["tā", "ka"] },
      { "greek": "δύνασθαι", "latvian": ["var"] },
      { "greek": "ὑπὸ", "latvian": ["apakš"] },
      { "greek": "τὴν", "latvian": [] },
      { "greek": "σκιὰν", "latvian": ["pavēnī"] },
      { "greek": "αὐτοῦ", "latvian": ["viņa"] },
      { "greek": "τὰ", "latvian": [] },
      { "greek": "πετεινὰ", "latvian": ["putni"] },
      { "greek": "τοῦ", "latvian": [] },
      { "greek": "οὐρανοῦ", "latvian": ["debess"] },
      { "greek": "κατασκηνοῦν", "latvian": ["ligzdas", "taisīt"] }
    ],
    "leftover_latvian": ["tas", "ir", "tad", "tas", "par"]
  },
  {
    "greek_words": [
      { "greek": "Καὶ", "latvian": ["Un"] },
      { "greek": "τοιαύταις", "latvian": ["tādās"] },
      { "greek": "παραβολαῖς", "latvian": ["līdzībās"] },
      { "greek": "πολλαῖς", "latvian": ["daudzās"] },
      { "greek": "ἐλάλει", "latvian": ["runāja"] },
      { "greek": "αὐτοῖς", "latvian": ["tiem"] },
      { "greek": "τὸν", "latvian": ["vārdu"] },
      { "greek": "λόγον", "latvian": [] },
      { "greek": "καθὼς", "latvian": ["tā", "ka"] },
      { "greek": "ἠδύναντο", "latvian": ["varēja"] },
      { "greek": "ἀκούειν", "latvian": ["klausīties"] }
    ],
    "leftover_latvian": ["Viņš", "uz", "tie", "to"]
  },
  {
    "greek_words": [
      { "greek": "χωρὶς", "latvian": ["bez"] },
      { "greek": "δὲ", "latvian": ["Bet"] },
      { "greek": "παραβολῆς", "latvian": ["līdzībām"] },
      { "greek": "οὐκ", "latvian": ["neko"] },
      { "greek": "ἐλάλει", "latvian": ["nerunāja"] },
      { "greek": "αὐτοῖς", "latvian": ["tiem"] },
      { "greek": "κατ", "latvian": ["uz"] },
      { "greek": "ἰδίαν", "latvian": ["īpaši"] },
      { "greek": "δὲ", "latvian": ["bet"] },
      { "greek": "τοῖς", "latvian": ["Saviem"] },
      { "greek": "ἰδίοις", "latvian": [] },
      { "greek": "μαθηταῖς", "latvian": ["mācekļiem"] },
      { "greek": "ἐπέλυεν", "latvian": ["izskaidroja"] },
      { "greek": "πάντα", "latvian": ["visu"] }
    ],
    "leftover_latvian": ["Viņš", "Viņš"]
  },
  {
    "greek_words": [
      { "greek": "Καὶ", "latvian": ["Un"] },
      { "greek": "λέγει", "latvian": ["saka"] },
      { "greek": "αὐτοῖς", "latvian": ["tiem"] },
      { "greek": "ἐν", "latvian": [] },
      { "greek": "ἐκείνῃ", "latvian": ["tanī"] },
      { "greek": "τῇ", "latvian": [] },
      { "greek": "ἡμέρᾳ", "latvian": ["dienā"] },
      { "greek": "ὀψίας", "latvian": ["vakaram"] },
      { "greek": "γενομένης", "latvian": ["metoties"] },
      { "greek": "Διέλθωμεν", "latvian": ["Pārcelsimies"] },
      { "greek": "εἰς", "latvian": ["uz"] },
      { "greek": "τὸ", "latvian": [] },
      { "greek": "πέραν", "latvian": ["malu"] }
    ],
    "leftover_latvian": ["Viņš", "viņu"]
  },
  {
    "greek_words": [
      { "greek": "καὶ", "latvian": ["Un"] },
      { "greek": "ἀφέντες", "latvian": ["atlaiduši"] },
      { "greek": "τὸν", "latvian": [] },
      { "greek": "ὄχλον", "latvian": ["ļaudis"] },
      { "greek": "παραλαμβάνουσιν", "latvian": ["ņēma"] },
      { "greek": "αὐτὸν", "latvian": ["Viņu"] },
      { "greek": "ὡς", "latvian": ["tā"] },
      { "greek": "ἦν", "latvian": ["bija"] },
      { "greek": "ἐν", "latvian": [] },
      { "greek": "τῷ", "latvian": [] },
      { "greek": "πλοίῳ", "latvian": ["laivā"] },
      { "greek": "καὶ", "latvian": ["un"] },
      { "greek": "ἄλλα", "latvian": ["citas"] },
      { "greek": "πλοῖα", "latvian": ["laivas"] },
      { "greek": "ἦν", "latvian": ["bija"] },
      { "greek": "μετ", "latvian": ["pie"] },
      { "greek": "αὐτοῦ", "latvian": ["Viņa"] }
    ],
    "leftover_latvian": ["tie", "līdzi", "ka", "Viņš"]
  },
  {
    "greek_words": [
      { "greek": "Καὶ", "latvian": ["Un"] },
      { "greek": "γίνεται", "latvian": ["cēlās"] },
      { "greek": "λαῖλαψ", "latvian": ["vētra"] },
      { "greek": "μεγάλη", "latvian": ["liela"] },
      { "greek": "ἀνέμου", "latvian": [] },
      { "greek": "καὶ", "latvian": ["un"] },
      { "greek": "τὰ", "latvian": [] },
      { "greek": "κύματα", "latvian": ["viļņi"] },
      { "greek": "ἐπέβαλλεν", "latvian": ["gāzās"] },
      { "greek": "εἰς", "latvian": [] },
      { "greek": "τὸ", "latvian": [] },
      { "greek": "πλοῖον", "latvian": ["laivā"] },
      { "greek": "ὥστε", "latvian": ["tā", "ka"] },
      { "greek": "ἤδη", "latvian": ["jau"] },
      { "greek": "γεμίζεσθαι", "latvian": ["piepildīja"] },
      { "greek": "τὸ", "latvian": [] },
      { "greek": "πλοῖον", "latvian": ["laivu"] }
    ],
    "leftover_latvian": ["ūdens"]
  },
  {
    "greek_words": [
      { "greek": "καὶ", "latvian": ["un"] },
      { "greek": "αὐτὸς", "latvian": ["Viņš"] },
      { "greek": "ἦν", "latvian": ["gulēja"] },
      { "greek": "ἐν", "latvian": ["galā"] },
      { "greek": "τῇ", "latvian": [] },
      { "greek": "πρύμνῃ", "latvian": ["stūres"] },
      { "greek": "ἐπὶ", "latvian": ["uz"] },
      { "greek": "τὸ", "latvian": [] },
      { "greek": "προσκεφάλαιον", "latvian": ["spilvena"] },
      { "greek": "καθεύδων", "latvian": [] },
      { "greek": "καὶ", "latvian": ["un"] },
      { "greek": "ἐγείρουσιν", "latvian": ["modina"] },
      { "greek": "αὐτὸν", "latvian": ["Viņu"] },
      { "greek": "καὶ", "latvian": ["un"] },
      { "greek": "λέγουσιν", "latvian": ["saka"] },
      { "greek": "αὐτῷ", "latvian": ["Viņam"] },
      { "greek": "Διδάσκαλε", "latvian": ["Mācītāj"] },
      { "greek": "οὐ", "latvian": ["nebēdā"] },
      { "greek": "μέλει", "latvian": [] },
      { "greek": "σοι", "latvian": ["Tu"] },
      { "greek": "ὅτι", "latvian": ["ka"] },
      { "greek": "ἀπολλύμεθα", "latvian": ["ejam", "bojā"] }
    ],
    "leftover_latvian": ["tie", "vai"]
  },
  {
    "greek_words": [
      { "greek": "Καὶ", "latvian": ["Un"] },
      { "greek": "διεγερθεὶς", "latvian": ["uzmodies"] },
      { "greek": "ἐπετίμησεν", "latvian": ["apsauca"] },
      { "greek": "τῷ", "latvian": [] },
      { "greek": "ἀνέμῳ", "latvian": ["vēju"] },
      { "greek": "καὶ", "latvian": ["un"] },
      { "greek": "εἶπεν", "latvian": ["sacīja"] },
      { "greek": "τῇ", "latvian": [] },
      { "greek": "θαλάσσῃ", "latvian": ["jūru"] },
      { "greek": "Σιώπα", "latvian": ["Klusu"] },
      { "greek": "πεφίμωσο", "latvian": ["mierā"] },
      { "greek": "καὶ", "latvian": ["Un"] },
      { "greek": "ἐκόπασεν", "latvian": ["nostājās"] },
      { "greek": "ὁ", "latvian": [] },
      { "greek": "ἄνεμος", "latvian": ["vējš"] },
      { "greek": "καὶ", "latvian": ["un"] },
      { "greek": "ἐγένετο", "latvian": ["iestājās"] },
      { "greek": "γαλήνη", "latvian": ["pilnīgs"] },
      { "greek": "μεγάλη", "latvian": ["klusums"] }
    ],
    "leftover_latvian": ["Viņš", "uz"]
  },
  {
    "greek_words": [
      { "greek": "Καὶ", "latvian": ["Un"] },
      { "greek": "εἶπεν", "latvian": ["sacīja"] },
      { "greek": "αὐτοῖς", "latvian": ["tiem"] },
      { "greek": "Τί", "latvian": ["Kam"] },
      { "greek": "δειλοί", "latvian": ["bailīgi"] },
      { "greek": "ἐστε", "latvian": ["esat"] },
      { "greek": "οὔπω", "latvian": [] },
      { "greek": "ἔχετε", "latvian": ["nav"] },
      { "greek": "πίστιν", "latvian": ["ticības"] }
    ],
    "leftover_latvian": ["Viņš", "uz", "jūs", "tik", "Kā", "jums"]
  },
  {
    "greek_words": [
      { "greek": "Καὶ", "latvian": ["Un"] },
      { "greek": "ἐφοβήθησαν", "latvian": ["izbijās"] },
      { "greek": "φόβον", "latvian": [] },
      { "greek": "μέγαν", "latvian": ["ļoti"] },
      { "greek": "καὶ", "latvian": ["un"] },
      { "greek": "ἔλεγον", "latvian": ["sacīja"] },
      { "greek": "πρὸς", "latvian": ["savā"] },
      { "greek": "ἀλλήλους", "latvian": ["starpā"] },
      { "greek": "Τίς", "latvian": ["Kas"] },
      { "greek": "ἄρα", "latvian": ["tāds"] },
      { "greek": "οὗτός", "latvian": ["Tas"] },
      { "greek": "ἐστιν", "latvian": [] },
      { "greek": "ὅτι", "latvian": ["ka"] },
      { "greek": "καὶ", "latvian": ["un"] },
      { "greek": "ὁ", "latvian": [] },
      { "greek": "ἄνεμος", "latvian": ["vējš"] },
      { "greek": "καὶ", "latvian": [] },
      { "greek": "ἡ", "latvian": [] },
      { "greek": "θάλασσα", "latvian": ["jūra"] },
      { "greek": "ὑπακούει", "latvian": ["paklausa"] },
      { "greek": "αὐτῷ", "latvian": ["Viņam"] }
    ],
    "leftover_latvian": ["tie", "pat"]
  }
]